extract_list/__init__.py
extract_list/__main__.py
extract_list/commontypes.py
extract_list/config_enums.py
extract_list/extract_cmd.py
extract_list/extract_config.py
extract_list/extract_data.py
extract_list/extract_func.py
extract_list/generate_cfg.py
extract_list/generate_txt_ex_common.py
extract_list/generate_txt_example_json.py
extract_list/generate_txt_example_xml.py
extract_list/generate_txt_sw_to_rrs.py
extract_list/generate_txt_syntax.py
extract_list/handle_input.py
extract_list/handle_json_xml_output.py
extract_list/handle_output.py
extract_list/handle_txt_output.py
extract_list/py.typed
extract_list/xl_version.py
extract_list-0.2.11.dist-info/licenses/LICENSE.txt
extract_list-0.2.11.dist-info/METADATA
extract_list-0.2.11.dist-info/WHEEL
extract_list-0.2.11.dist-info/top_level.txt
extract_list-0.2.11.dist-info/RECORD
