Metadata-Version: 2.4
Name: extract-list
Version: 0.2.11
Summary: Extract a list from JSON or XML, save to excel, csv, etc.
Author: Tom Björkholm
Author-email: Tom Björkholm <klausuler_linnet0q@icloud.com>
Project-URL: Source code, https://bitbucket.org/tom-bjorkholm/extract-list
Classifier: Programming Language :: Python :: 3
Classifier: License :: OSI Approved :: MIT License
Classifier: Operating System :: OS Independent
Requires-Python: >=3.13
License-File: LICENSE.txt
Requires-Dist: argcomplete>=3.6.2
Requires-Dist: excel-list-transform>=0.8.3
Requires-Dist: xmltodict>=0.14.2
Requires-Dist: types-xmltodict>=0.14.0.20241009
Requires-Dist: pip>=25.1.1
Requires-Dist: setuptools>=80.9.0
Requires-Dist: build>=1.2.2.post1
Requires-Dist: wheel>=0.45.1
Dynamic: author
Dynamic: license-file
Dynamic: requires-dist
Dynamic: requires-python
